buymeacoffee_api/__init__.py
buymeacoffee_api/core.py
buymeacoffee_api/src/constants.py
buymeacoffee_api/src/types.py
buymeacoffee_api-0.1.0.dist-info/METADATA
buymeacoffee_api-0.1.0.dist-info/WHEEL
buymeacoffee_api-0.1.0.dist-info/RECORD
